qml_essentials/__init__.py
qml_essentials/ansaetze.py
qml_essentials/coefficients.py
qml_essentials/entanglement.py
qml_essentials/expressibility.py
qml_essentials/model.py
qml_essentials/qoc.py
qml_essentials/qoc_results.csv
qml_essentials/utils.py
qml_essentials-0.1.37.dist-info/METADATA
qml_essentials-0.1.37.dist-info/WHEEL
qml_essentials-0.1.37.dist-info/licenses/LICENSE
qml_essentials-0.1.37.dist-info/RECORD
