Metadata-Version: 2.4
Name: qml-essentials
Version: 0.1.37
Summary: A toolbox to make working with QML models easier.
Project-URL: Homepage, https://cirkiters.github.io/qml-essentials/
Project-URL: Repository, https://github.com/cirKITers/qml-essentials
Project-URL: Documentation, https://cirkiters.github.io/qml-essentials/
Author-email: Melvin Strobl <melvin.strobl@kit.edu>, Maja Franz <maja.franz@oth-regensburg.de>
Maintainer-email: Melvin Strobl <melvin.strobl@kit.edu>
License-Expression: MIT
License-File: LICENSE
Keywords: qml,quantum,quantum machine learning
Requires-Python: <3.13,>=3.10
Requires-Dist: dill<0.5,>=0.4.0
Requires-Dist: jax<0.5,>=0.4.28
Requires-Dist: jaxlib<0.5,>=0.4.28
Requires-Dist: optax<0.3,>=0.2.5
Requires-Dist: pennylane<0.41.0,>=0.40.0
